{
  "sectionTitle": "New Releases",
  "sectionDescription": "Discover our latest publications that explore history, science, and philosophy through the eyes of animals",
  "viewAllLink": "#all-releases",
  "books": [
    {
      "id": 1,
      "title": "Animal Intelligence\nThe Book of Forgotten History",
      "description": "A retelling of history from the eye of extinct animals",
      "coverImage": "/images/books/History.svg",
      "coverStyle": "background: linear-gradient(135deg, #ffffff 0%, #f0f0f0 100%);"
    },
    {
      "id": 2,
      "title": "Guidebook to the AIU\nWhere the Ark lies Hidden",
      "description": "A guidebook that maps where AIU animals live across the world and what roles they play today",
      "coverImage": "/images/books/Guide.svg",
      "coverStyle": "background: linear-gradient(135deg, #4facfe 0%, #00f2fe 100%);"
    },
    {
      "id": 3,
      "title": "AI Short Comics Vol.1",
      "description": "A light philosophical comic about animals’ daily lives and the emotions they feel while observing human society\n(Coming Soon)",
      "coverImage": "/images/books/Comic1.svg",
      "coverStyle": "background: linear-gradient(135deg, #fa709a 0%, #fee140 100%);"
    }
  ]
}

